bstats/__init__.py
bstats/battlelog.py
bstats/brawler.py
bstats/client.py
bstats/club.py
bstats/errors.py
bstats/http.py
bstats/leaderboard.py
bstats/member.py
bstats/profile.py
bstats/rotation.py
bstats/utils.py
bstats-1.1.2.dist-info/LICENSE
bstats-1.1.2.dist-info/METADATA
bstats-1.1.2.dist-info/WHEEL
bstats-1.1.2.dist-info/top_level.txt
bstats-1.1.2.dist-info/RECORD
