Metadata-Version: 2.1
Name: bstats
Version: 1.1.2
Summary: A fundamental wrapper for the Brawl Stars API covering all endpoints and including many features!
Home-page: https://github.com/Bimi05/bstats
Author: Bimi05
Author-email: dim.ziakas07@gmail.com
Project-URL: Issues, https://github.com/Bimi05/bstats/issues
Classifier: Development Status :: 5 - Production/Stable
Classifier: Intended Audience :: Developers
Classifier: Programming Language :: Python :: 3.8
Classifier: Programming Language :: Python :: 3.9
Classifier: License :: OSI Approved :: MIT License
Classifier: Topic :: Games/Entertainment :: Real Time Strategy
Classifier: Natural Language :: English
Requires-Python: >=3.8
License-File: LICENSE
Requires-Dist: aiohttp (<3.9,>=3.8.0)
Requires-Dist: cachetools (>=4.1.0)
Requires-Dist: requests
